bfs_mro/__init__.py
bfs_mro/core.py
bfs_mro-0.1.3.dist-info/licenses/LICENSE
bfs_mro-0.1.3.dist-info/METADATA
bfs_mro-0.1.3.dist-info/WHEEL
bfs_mro-0.1.3.dist-info/top_level.txt
bfs_mro-0.1.3.dist-info/RECORD
