Metadata-Version: 2.4
Name: bfs_mro
Version: 0.1.3
Summary: Context manager that extends MRO with BFS lookup in subclasses
Author-email: Alexander Shchukin <446.54.53@gmail.com>
License-Expression: MIT
Project-URL: Repository, https://github.com/AlexShchW/bfs_mro.git
Requires-Python: >=3.9
License-File: LICENSE
Provides-Extra: dev
Requires-Dist: pytest; extra == "dev"
Requires-Dist: pytest-cov; extra == "dev"
Dynamic: license-file
